mavecore/__init__.py
mavecore/original_validation/__init__.py
mavecore/original_validation/constants.py
mavecore/original_validation/dataset_validators.py
mavecore/original_validation/exceptions.py
mavecore/original_validation/genome_validators.py
mavecore/original_validation/metadata_validators.py
mavecore/original_validation/urn_validators.py
mavecore/original_validation/validate.py
mavecore/original_validation/variant_validators/__init__.py
mavecore/original_validation/variant_validators/dataset.py
mavecore/original_validation/variant_validators/hgvs.py
mavecore/original_validation/variant_validators/variant.py
mavecore/validation/__init__.py
mavecore/validation/constants.py
mavecore/validation/dataset_validators.py
mavecore/validation/exceptions.py
mavecore/validation/general_validators.py
mavecore/validation/genome_validators.py
mavecore/validation/metadata_validators.py
mavecore/validation/urn_validators.py
mavecore/validation/utilities.py
mavecore/validation/validate.py
mavecore/validation/variant_validators/__init__.py
mavecore/validation/variant_validators/dataset.py
mavecore/validation/variant_validators/hgvs.py
mavecore/validation/variant_validators/variant.py
tests/__init__.py
tests/test_validation/__init__.py
tests/test_validation/test_dataset_validators.py
tests/test_validation/test_genome_validators.py
tests/test_validation/test_metadata_validators.py
tests/test_validation/test_variant_validators/__init__.py
tests/test_validation/test_variant_validators/test_hgvs_validators.py
tests/test_validation/test_variant_validators/test_validators.py
mavecore-0.1.7.dist-info/LICENSE
mavecore-0.1.7.dist-info/METADATA
mavecore-0.1.7.dist-info/WHEEL
mavecore-0.1.7.dist-info/top_level.txt
mavecore-0.1.7.dist-info/RECORD
